bodge/engine.py
brick_bodge-0.2.0.dist-info/LICENSE
brick_bodge-0.2.0.dist-info/WHEEL
brick_bodge-0.2.0.dist-info/METADATA
brick_bodge-0.2.0.dist-info/RECORD
