Metadata-Version: 2.1
Name: brick-bodge
Version: 0.2.0
Summary: Rule-based framework for building Brick models from simple functions
License: BSD-3-Clause
Author: Gabe Fierro
Author-email: gtfierro@mines.edu
Requires-Python: >=3.7,<4.0
Classifier: License :: OSI Approved :: BSD License
Classifier: Programming Language :: Python :: 3
Classifier: Programming Language :: Python :: 3.10
Classifier: Programming Language :: Python :: 3.7
Classifier: Programming Language :: Python :: 3.8
Classifier: Programming Language :: Python :: 3.9
Requires-Dist: brickschema (>=0.5.1,<0.6.0)
Requires-Dist: rdflib (>=6.0.2,<7.0.0)
